README.rst
setup.py
machobot/__init__.py
machobot/command_line.py
machobot/dylib.py
machobot.egg-info/PKG-INFO
machobot.egg-info/SOURCES.txt
machobot.egg-info/dependency_links.txt
machobot.egg-info/entry_points.txt
machobot.egg-info/not-zip-safe
machobot.egg-info/requires.txt
machobot.egg-info/top_level.txt
machobot/common/__init__.py
machobot/common/fileutils.py
machobot/common/macho_helpers.py
machobot/tests/__init__.py
machobot/tests/test_dylib.py