Metadata-Version: 1.1
Name: machobot
Version: 0.1.5
Summary: A set of tools for Mach-O executables analysis on OS X
Home-page: http://github.com/rodionovd/machobot
Author: Dmitry Rodionov
Author-email: i.am.rodionovd@gmail.com
License: MIT
Platform: UNKNOWN
Classifier: Development Status :: 3 - Alpha
Classifier: License :: OSI Approved :: MIT License
